mukkeBude/__init__.py
mukkeBude/mapping.py
mukkeBude/model/__init__.py
mukkeBude/model/mukke_bude_lstm.py
mukkeBude/model/mukke_bude_transformer.py
mukkeBude/songs/generated_song_pokemon.mid
mukkeBude/utils.py
mukkebude-0.1.2.dist-info/METADATA
mukkebude-0.1.2.dist-info/WHEEL
mukkebude-0.1.2.dist-info/RECORD
