Metadata-Version: 2.1
Name: mukkebude
Version: 0.1.2
Summary: A music generation library with transformer and lstm models',
Home-page: https://github.com/DHBW-FN-TIT20/Komposition-eines-Musikstuecks-mittels-Neuronaler-Netze
Author: Florian Glaser
Author-email: Florian.Glaser@ifm.com
Requires-Python: >=3.9,<3.12
Classifier: Programming Language :: Python :: 3
Classifier: Programming Language :: Python :: 3.9
Classifier: Programming Language :: Python :: 3.10
Classifier: Programming Language :: Python :: 3.11
Requires-Dist: keras-nlp (==0.4.1)
Requires-Dist: matplotlib (>=3.7.1,<4.0.0)
Requires-Dist: music21 (>=8.1.0,<9.0.0)
Requires-Dist: sacremoses (==0.0.53)
Requires-Dist: tensorflow (>=2.10.0,<2.11.0)
Requires-Dist: tensorflow-io-gcs-filesystem (==0.31.0)
Requires-Dist: tensorflow-text (==2.10.0)
Project-URL: Repository, https://github.com/DHBW-FN-TIT20/Komposition-eines-Musikstuecks-mittels-Neuronaler-Netze
